{
  "home_page": {
    "work_title": "Software Engineer and Business Developer",
    "welcome_message": "Welcome to my personal corner on the web! Feel free to explore and discover more about me, my journey, and the projects I’m passionate about."
  },
  "page_not_found": "404 - Page not found",
  "navbar_menu": {
    "home": "Home",
    "career": "Career",
    "portfolio": "Portfolio",
    "interests": "Interests",
    "contact": "Contact"
  },
  "contact_page": {
    "path_to_cv": "CV-tasnim-eng.pdf",
    "email_button_label": "write to me",
    "linkedin_button_label": "join my network",
    "git_button_label": "check out my git"
  }
}
